MANIFEST.in
setup.py
tyler.py
pytyler.egg-info/PKG-INFO
pytyler.egg-info/SOURCES.txt
pytyler.egg-info/dependency_links.txt
pytyler.egg-info/entry_points.txt
pytyler.egg-info/not-zip-safe
pytyler.egg-info/requires.txt
pytyler.egg-info/top_level.txt