Metadata-Version: 1.1
Name: pytyler
Version: 0.1.6
Summary: a simple Python tail
Home-page: http://github.com/mastro35/tyler/
Author: Davide Mastromatteo
Author-email: dave35@me.com
License: Apache-2.0
Platform: any
Classifier: Development Status :: 4 - Beta
Classifier: Intended Audience :: Developers
Classifier: License :: OSI Approved :: Apache Software License
Classifier: Operating System :: OS Independent
Classifier: Programming Language :: Python :: 3.5
